vettly/__init__.py
vettly/client.py
vettly/exceptions.py
vettly/models.py
vettly/py.typed
vettly-0.1.4.dist-info/METADATA
vettly-0.1.4.dist-info/WHEEL
vettly-0.1.4.dist-info/licenses/LICENSE
vettly-0.1.4.dist-info/RECORD
