Metadata-Version: 2.4
Name: vettly
Version: 0.1.4
Summary: Python SDK for Vettly content moderation API
Project-URL: Homepage, https://vettly.dev
Project-URL: Documentation, https://docs.vettly.dev
Project-URL: Repository, https://github.com/nextauralabs/vettly
Project-URL: Issues, https://github.com/nextauralabs/vettly/issues
Project-URL: Source Code, https://github.com/nextauralabs/vettly
Project-URL: Bug Tracker, https://github.com/nextauralabs/vettly/issues
Author-email: Nextura Labs <support@vettly.dev>
Maintainer-email: Nextura Labs <support@vettly.dev>
License-Expression: MIT
License-File: LICENSE
Keywords: ai,api,content-moderation,machine-learning,moderation,safety,sdk
Classifier: Development Status :: 4 - Beta
Classifier: Intended Audience :: Developers
Classifier: License :: OSI Approved :: MIT License
Classifier: Operating System :: OS Independent
Classifier: Programming Language :: Python :: 3
Classifier: Programming Language :: Python :: 3.8
Classifier: Programming Language :: Python :: 3.9
Classifier: Programming Language :: Python :: 3.10
Classifier: Programming Language :: Python :: 3.11
Classifier: Programming Language :: Python :: 3.12
Classifier: Topic :: Internet :: WWW/HTTP
Classifier: Topic :: Software Development :: Libraries :: Python Modules
Classifier: Typing :: Typed
Requires-Python: >=3.8
Requires-Dist: httpx>=0.24.0
Requires-Dist: pydantic>=2.0.0
Provides-Extra: async
Requires-Dist: httpx[http2]>=0.24.0; extra == 'async'
Provides-Extra: dev
Requires-Dist: mypy>=1.0.0; extra == 'dev'
Requires-Dist: pytest-asyncio>=0.21.0; extra == 'dev'
Requires-Dist: pytest-httpx>=0.21.0; extra == 'dev'
Requires-Dist: pytest>=7.0.0; extra == 'dev'
Requires-Dist: ruff>=0.1.0; extra == 'dev'
